<?xml version="1.0" ?><root>	<tp i="1">		<enable>1</enable>		<pin lev="1">12345</pin>		<pin lev="2">11223</pin>		<pin lev="3">99999</pin>	</tp>	<tp i="2">		<enable>1</enable>		<pin lev="1">12345</pin>		<pin lev="2">54321</pin>		<pin lev="3">99999</pin>	</tp>	<tp i="3">		<enable>1</enable>		<pin lev="1">12345</pin>		<pin lev="2">54321</pin>		<pin lev="3">99999</pin>	</tp>	<tp i="4">		<enable>1</enable>		<pin lev="1">12345</pin>		<pin lev="2">54321</pin>		<pin lev="3">99999</pin>	</tp>	<tp i="5">		<enable>1</enable>		<pin lev="1">12345</pin>		<pin lev="2">54321</pin>		<pin lev="3">99999</pin>	</tp>	<tp i="6">		<enable>1</enable>		<pin lev="1">12345</pin>		<pin lev="2">54321</pin>		<pin lev="3">99999</pin>	</tp>	<tp i="7">		<enable>1</enable>		<pin lev="1">12345</pin>		<pin lev="2">54321</pin>		<pin lev="3">99999</pin>	</tp>	<tp i="8">		<enable>1</enable>		<pin lev="1">12345</pin>		<pin lev="2">54321</pin>		<pin lev="3">99999</pin>	</tp>	<tp i="9">		<enable>1</enable>		<pin lev="1">12345</pin>		<pin lev="2">54321</pin>		<pin lev="3">99999</pin>	</tp>	<tp i="10">		<enable>1</enable>		<pin lev="1">12345</pin>		<pin lev="2">54321</pin>		<pin lev="3">99999</pin>	</tp>	<tp i="11">		<enable>1</enable>		<pin lev="1">12345</pin>		<pin lev="2">54321</pin>		<pin lev="3">99999</pin>	</tp>	<tp i="12">		<enable>1</enable>		<pin lev="1">12345</pin>		<pin lev="2">54321</pin>		<pin lev="3">99999</pin>	</tp>	<tp i="13">		<enable>1</enable>		<pin lev="1">12345</pin>		<pin lev="2">54321</pin>		<pin lev="3">99999</pin>	</tp>	<tp i="14">		<enable>1</enable>		<pin lev="1">12345</pin>		<pin lev="2">54321</pin>		<pin lev="3">99999</pin>	</tp>	<tp i="15">		<enable>1</enable>		<pin lev="1">12345</pin>		<pin lev="2">54321</pin>		<pin lev="3">99999</pin>	</tp>	<tp i="16">		<enable>1</enable>		<pin lev="1">12345</pin>		<pin lev="2">54321</pin>		<pin lev="3">99999</pin>	</tp>	<tp i="17">		<enable>1</enable>		<pin lev="1">12345</pin>		<pin lev="2">54321</pin>		<pin lev="3">99999</pin>	</tp>	<tp i="18">		<enable>1</enable>		<pin lev="1">12345</pin>		<pin lev="2">54321</pin>		<pin lev="3">99999</pin>	</tp>	<tp i="19">		<enable>1</enable>		<pin lev="1">12345</pin>		<pin lev="2">54321</pin>		<pin lev="3">99999</pin>	</tp>	<tp i="20">		<enable>1</enable>		<pin lev="1">12345</pin>		<pin lev="2">54321</pin>		<pin lev="3">99999</pin>	</tp>	<tp i="21">		<enable>1</enable>		<pin lev="1">12345</pin>		<pin lev="2">54321</pin>		<pin lev="3">99999</pin>	</tp>	<tp i="22">		<enable>1</enable>		<pin lev="1">12345</pin>		<pin lev="2">54321</pin>		<pin lev="3">99999</pin>	</tp>	<tp i="23">		<enable>1</enable>		<pin lev="1">12345</pin>		<pin lev="2">54321</pin>		<pin lev="3">99999</pin>	</tp>	<tp i="24">		<enable>1</enable>		<pin lev="1">12345</pin>		<pin lev="2">54321</pin>		<pin lev="3">99999</pin>	</tp>	<tp i="25">		<enable>1</enable>		<pin lev="1">12345</pin>		<pin lev="2">54321</pin>		<pin lev="3">99999</pin>	</tp></root>